Metadata-Version: 1.2
Name: progress-counter
Version: 0.0.1
Summary: simple text progress counter
Home-page: UNKNOWN
Author: Casey Marks
Author-email: casey@carveacre.com
License: UNKNOWN
Platform: UNKNOWN
Classifier: Programming Language :: Python :: 3
Classifier: License :: OSI Approved :: MIT License
Classifier: Operating System :: OS Independent
Requires-Python: >=3.6
